MANIFEST.in
README.txt
setup.cfg
setup.py
docs/HISTORY.txt
horae/__init__.py
horae.calendar.egg-info/PKG-INFO
horae.calendar.egg-info/SOURCES.txt
horae.calendar.egg-info/dependency_links.txt
horae.calendar.egg-info/entry_points.txt
horae.calendar.egg-info/namespace_packages.txt
horae.calendar.egg-info/not-zip-safe
horae.calendar.egg-info/requires.txt
horae.calendar.egg-info/top_level.txt
horae/calendar/__init__.py
horae/calendar/configure.zcml
horae/calendar/interfaces.py
horae/calendar/resource.py
horae/calendar/views.py
horae/calendar/locales/horae.calendar.pot
horae/calendar/locales/de/LC_MESSAGES/horae.calendar.mo
horae/calendar/locales/de/LC_MESSAGES/horae.calendar.po
horae/calendar/static/calendar.css
horae/calendar/static/calendar.js
horae/calendar/templates/calendar.cpt