Metadata-Version: 1.0
Name: horae.calendar
Version: 1.0a1
Summary: Provides generic calendar views (month, week and day) using horae.timeaware
Home-page: UNKNOWN
Author: Simon Kaeser
Author-email: skaeser@gmail.com
License: GPL
Platform: UNKNOWN
Classifier: Programming Language :: Python
